pyfeishu/__init__.py
pyfeishu/__version__.py
pyfeishu/bot.py
pyfeishu/errors.py
pyfeishu/log.py
PyFeishu-0.2.3.dist-info/LICENSE
PyFeishu-0.2.3.dist-info/METADATA
PyFeishu-0.2.3.dist-info/WHEEL
PyFeishu-0.2.3.dist-info/top_level.txt
PyFeishu-0.2.3.dist-info/RECORD
