Metadata-Version: 2.1
Name: PyFeishu
Version: 0.2.3
Summary: This is a msg-robot for FeiShu.
Home-page: https://github.com/liukecode/pyfeishu
Author: LiuKeCode
Maintainer: Liuke
License: MIT
Keywords: feishu,api,bot,robot,sdk
Classifier: Development Status :: 5 - Production/Stable
Classifier: Intended Audience :: Developers
Classifier: Intended Audience :: End Users/Desktop
Classifier: Intended Audience :: Information Technology
Classifier: Intended Audience :: System Administrators
Classifier: License :: OSI Approved :: MIT License
Classifier: Programming Language :: Python :: 3.7
Classifier: Programming Language :: Python :: 3.8
Classifier: Programming Language :: Python :: 3.9
Classifier: Programming Language :: Python :: 3.10
Classifier: Topic :: Communications
Classifier: Topic :: Office/Business
Requires-Python: >=3.7
License-File: LICENSE
Requires-Dist: cachetools (==5.2.0)
Requires-Dist: requests (==2.26.0)
Requires-Dist: requests-toolbelt (==0.9.1)
Requires-Dist: tenacity (==8.0.1)
